Metadata-Version: 2.1
Name: test-wq
Version: 0.0.3
Summary: test for pypi
Home-page: https://github.com/osakemon/pypiTest
Author: wq
Author-email: osakemon@gmail.com
License: UNKNOWN
Platform: UNKNOWN
Classifier: Programming Language :: Python :: 3
Classifier: License :: OSI Approved :: MIT License
Classifier: Operating System :: OS Independent
License-File: LICENSE
